vkapi/__init__.py
vkapi/api.py
vkapi/exceptions.py
vkapi/session.py
vkapi/utils.py
vkapi_rmq_client-1.0.0.dist-info/METADATA
vkapi_rmq_client-1.0.0.dist-info/WHEEL
vkapi_rmq_client-1.0.0.dist-info/top_level.txt
vkapi_rmq_client-1.0.0.dist-info/RECORD
