Metadata-Version: 2.1
Name: vkapi-rmq-client
Version: 1.0.0
Summary: A library to work with vkAPIService. Useless if you don't have the service.
Home-page: https://github.com/cyber-chuvash/vkAPIClient
Author: Mikhail Migushov
Author-email: me@chuvash.pw
License: UNKNOWN
Platform: UNKNOWN
Classifier: Programming Language :: Python :: 3.7
Requires-Dist: pika
